jsonscreamer/__init__.py
jsonscreamer/array.py
jsonscreamer/basic.py
jsonscreamer/compile.py
jsonscreamer/format.py
jsonscreamer/logical.py
jsonscreamer/object_.py
jsonscreamer/resolve.py
jsonscreamer/types.py
jsonscreamer/_metaschemas/draft07.json
jsonscreamer-0.5.0.data/data/draft07.json
jsonscreamer-0.5.0.dist-info/licenses/LICENSE
jsonscreamer-0.5.0.dist-info/WHEEL
jsonscreamer-0.5.0.dist-info/METADATA
jsonscreamer-0.5.0.dist-info/RECORD
