Metadata-Version: 2.4
Name: jsonscreamer
Version: 0.5.0
Summary: fast json schema validator
Author: Oliver Margetts
Requires-Python: >=3.10
License-Expression: MIT
Classifier: Intended Audience :: Developers
Classifier: Operating System :: OS Independent
Classifier: Programming Language :: Python
Classifier: Programming Language :: Python :: 3.10
Classifier: Programming Language :: Python :: 3.11
Classifier: Programming Language :: Python :: 3.12
Classifier: Programming Language :: Python :: 3.13
Classifier: Programming Language :: Python :: Implementation :: CPython
Classifier: Programming Language :: Python :: Implementation :: PyPy
Classifier: Topic :: File Formats :: JSON
Classifier: Topic :: File Formats :: JSON :: JSON Schema
License-File: LICENSE
Requires-Dist: fastjsonschema
Requires-Dist: idna ; extra == "all-formats"
Requires-Dist: jsonpointer ; extra == "all-formats"
Requires-Dist: rfc3987 ; extra == "all-formats"
Requires-Dist: uri_template ; extra == "all-formats"
Requires-Dist: fqdn ; extra == "all-formats"
Requires-Dist: pytest ; extra == "dev"
Requires-Dist: jsonschema ; extra == "dev"
Requires-Dist: ruff ; extra == "dev"
Requires-Dist: pyright ; extra == "dev"
Requires-Dist: idna ; extra == "dev"
Requires-Dist: jsonpointer ; extra == "dev"
Requires-Dist: rfc3987 ; extra == "dev"
Requires-Dist: uri_template ; extra == "dev"
Requires-Dist: fqdn ; extra == "dev"
Provides-Extra: all-formats
Provides-Extra: dev
